objection/__init__.py
objection/courtroom/__init__.py
objection/courtroom/handlers.py
objection/courtroom/utils.py
objection/courtroom/types/__init__.py
objection/courtroom/types/events.py
python_objectionlol-0.0.5.dist-info/METADATA
python_objectionlol-0.0.5.dist-info/WHEEL
python_objectionlol-0.0.5.dist-info/top_level.txt
python_objectionlol-0.0.5.dist-info/RECORD
